filechecker/__init__.py
filechecker/admin.py
filechecker/apps.py
filechecker/arche_serializer.py
filechecker/arche_views.py
filechecker/fc_arche_urls.py
filechecker/filechecker_utils.py
filechecker/filters.py
filechecker/forms.py
filechecker/models.py
filechecker/tables.py
filechecker/tests.py
filechecker/urls.py
filechecker/views.py
filechecker/migrations/0001_initial.py
filechecker/migrations/__init__.py
filechecker/templates/filechecker/fc_collection_detail.html
filechecker/templates/filechecker/fc_resource_detail.html
acdh_django_filechecker-0.0.2.dist-info/LICENSE.txt
acdh_django_filechecker-0.0.2.dist-info/METADATA
acdh_django_filechecker-0.0.2.dist-info/WHEEL
acdh_django_filechecker-0.0.2.dist-info/top_level.txt
acdh_django_filechecker-0.0.2.dist-info/RECORD
